odoo/addons/l10n_it_vat_statement_communication/README.rst
odoo/addons/l10n_it_vat_statement_communication/__init__.py
odoo/addons/l10n_it_vat_statement_communication/__manifest__.py
odoo/addons/l10n_it_vat_statement_communication/data/comunicazioneIvp_2017_v1.xsd
odoo/addons/l10n_it_vat_statement_communication/data/fornituraIvp_2017_v1.xsd
odoo/addons/l10n_it_vat_statement_communication/data/fornitura_v3.xsd
odoo/addons/l10n_it_vat_statement_communication/data/intestazioneIvp_2017_v1.xsd
odoo/addons/l10n_it_vat_statement_communication/data/typesDati_v3.xsd
odoo/addons/l10n_it_vat_statement_communication/data/typesProvincie_v3.xsd
odoo/addons/l10n_it_vat_statement_communication/i18n/it.po
odoo/addons/l10n_it_vat_statement_communication/i18n/l10n_it_vat_statement_communication.pot
odoo/addons/l10n_it_vat_statement_communication/models/__init__.py
odoo/addons/l10n_it_vat_statement_communication/models/account.py
odoo/addons/l10n_it_vat_statement_communication/models/comunicazione_liquidazione.py
odoo/addons/l10n_it_vat_statement_communication/models/config.py
odoo/addons/l10n_it_vat_statement_communication/readme/CONFIGURE.md
odoo/addons/l10n_it_vat_statement_communication/readme/CONTRIBUTORS.md
odoo/addons/l10n_it_vat_statement_communication/readme/DESCRIPTION.md
odoo/addons/l10n_it_vat_statement_communication/readme/USAGE.md
odoo/addons/l10n_it_vat_statement_communication/security/ir.model.access.csv
odoo/addons/l10n_it_vat_statement_communication/security/security.xml
odoo/addons/l10n_it_vat_statement_communication/static/description/icon.png
odoo/addons/l10n_it_vat_statement_communication/static/description/index.html
odoo/addons/l10n_it_vat_statement_communication/tests/__init__.py
odoo/addons/l10n_it_vat_statement_communication/tests/test_vat_statement_communication.py
odoo/addons/l10n_it_vat_statement_communication/views/account.xml
odoo/addons/l10n_it_vat_statement_communication/views/comunicazione_liquidazione.xml
odoo_addon_l10n_it_vat_statement_communication-16.0.1.0.1.dist-info/METADATA
odoo_addon_l10n_it_vat_statement_communication-16.0.1.0.1.dist-info/WHEEL
odoo_addon_l10n_it_vat_statement_communication-16.0.1.0.1.dist-info/top_level.txt
odoo_addon_l10n_it_vat_statement_communication-16.0.1.0.1.dist-info/RECORD
