Metadata-Version: 2.1
Name: odoo-addon-l10n_it_vat_statement_communication
Version: 16.0.1.0.1
Requires-Python: >=3.10
Requires-Dist: odoo-addon-account_vat_period_end_statement>=16.0dev,<16.1dev
Requires-Dist: odoo-addon-l10n_it_appointment_code>=16.0dev,<16.1dev
Requires-Dist: odoo-addon-l10n_it_fiscalcode>=16.0dev,<16.1dev
Requires-Dist: odoo>=16.0a,<16.1dev
Summary: Comunicazione liquidazione IVA ed esportazione file xmlconforme alle specifiche dell'Agenzia delle Entrate
Home-page: https://github.com/OCA/l10n-italy
License: AGPL-3
Author: Openforce di Camilli Alessandro, Odoo Community Association (OCA)
Author-email: support@odoo-community.org
Classifier: Programming Language :: Python
Classifier: Framework :: Odoo
Classifier: Framework :: Odoo :: 16.0
Classifier: License :: OSI Approved :: GNU Affero General Public License v3
